.gitignore
AUTHORS
CHANGELOG
FAQ
INSTALL
NEWS
README
THANKS
release.txt
setup.py
docs-build/Makefile
docs-build/_module.rst
docs-build/conf.py
docs-build/guard.rst
docs-build/index.rst
docs-build/introduction.rst
docs-build/modules.rst
docs-build/resources.rst
docs-build/restish.app.rst
docs-build/restish.error.rst
docs-build/restish.guard.rst
docs-build/restish.http.rst
docs-build/restish.page.rst
docs-build/restish.resource.rst
docs-build/restish.templating.rst
docs-build/restish.url.rst
docs-build/templating.rst
docs-build/wsgiapps.rst
docs-build/.static/.gitignore
docs-build/.static/css/clearfix.css
docs-build/.static/css/flash.css
docs-build/.static/css/formish.css
docs-build/.static/css/images.css
docs-build/.static/css/sIFR-print.css
docs-build/.static/css/sIFR-screen.css
docs-build/.static/css/screen.css
docs-build/.static/css/tripoli/tripoli.base.css
docs-build/.static/css/tripoli/tripoli.base.ie.css
docs-build/.static/css/tripoli/tripoli.css
docs-build/.static/css/tripoli/tripoli.ie.css
docs-build/.static/css/tripoli/tripoli.simple.css
docs-build/.static/css/tripoli/tripoli.simple.ie.css
docs-build/.static/css/tripoli/plugins/tripoli.layout.css
docs-build/.static/css/tripoli/plugins/tripoli.negative.css
docs-build/.static/css/tripoli/plugins/tripoli.type.css
docs-build/.static/css/tripoli/plugins/tripoli.visual.css
docs-build/.static/fonts/rockwellbold.swf
docs-build/.static/fonts/sifr-helveticacondensedroman.swf
docs-build/.static/fonts/sifr-rockwell.swf
docs-build/.static/images/bg/body.jpg
docs-build/.static/images/icon/error.png
docs-build/.static/images/icon/success.png
docs-build/.static/images/icon/warning.png
docs-build/.static/images/logo/ish.io.png
docs-build/.static/js/flash.js
docs-build/.static/js/formish.js
docs-build/.static/js/infomy.ui.js
docs-build/.static/js/jquery-1.2.6.min.js
docs-build/.static/js/jquery-ui-personalized-1.6rc2.packed.js
docs-build/.static/js/jquery.base64.js
docs-build/.static/js/sifr-config.js
restish.egg-info/PKG-INFO
restish.egg-info/SOURCES.txt
restish.egg-info/dependency_links.txt
restish.egg-info/entry_points.txt
restish.egg-info/not-zip-safe
restish.egg-info/requires.txt
restish.egg-info/top_level.txt
